selenium_recaptcha_solver/__init__.py
selenium_recaptcha_solver/api.py
selenium_recaptcha_solver/exceptions.py
selenium_recaptchav2_solver-0.0.3.dist-info/LICENSE
selenium_recaptchav2_solver-0.0.3.dist-info/METADATA
selenium_recaptchav2_solver-0.0.3.dist-info/WHEEL
selenium_recaptchav2_solver-0.0.3.dist-info/top_level.txt
selenium_recaptchav2_solver-0.0.3.dist-info/RECORD
