Metadata-Version: 2.1
Name: selenium-recaptchav2-solver
Version: 0.0.3
Summary: UNKNOWN
Home-page: https://github.com/thicccat688/selenium-recaptchav2-solver
Author: Tomás Perestrelo
Author-email: tomasperestrelo21@gmail.com
License: MIT
Download-URL: https://pypi.org/project/selenium-recaptchav2-solver
Keywords: python,captcha,speech recognition,selenium,web automation
Platform: UNKNOWN
License-File: LICENSE
Requires-Dist: requests
